{"q1":"Que signifie chmod 755 ?","a1":"Le propriétaire peut lire, écrire, exécuter (7). Le groupe et les autres peuvent lire et exécuter mais pas écrire (5).","q2":"Quelle est la différence entre 644 et 755 ?","a2":"644 donne au propriétaire la lecture/écriture, aux autres la lecture seule. 755 ajoute la permission d'exécution, généralement utilisé pour les répertoires et les scripts.","q3":"Quand devrais-je utiliser 777 ?","a3":"Presque jamais en production. 777 donne les permissions complètes à tout le monde, ce qui est un risque de sécurité. Utilisez-le uniquement pour les tests temporaires."}