{"q1":"What is compound interest?","a1":"Compound interest is interest calculated on both the initial principal and the accumulated interest from previous periods, leading to exponential growth.","q2":"What compounding frequencies are available?","a2":"Daily (365x/year), monthly (12x), quarterly (4x), and yearly (1x).","q3":"Can I add monthly contributions?","a3":"Yes, you can enter an optional monthly contribution amount to see how regular deposits accelerate growth.","q4":"How is compound interest calculated?","a4":"A = P(1 + r/n)^(nt) + PMT × [((1 + r/n)^(nt) - 1) / (r/n)], where P = principal, r = rate, n = frequency, t = time, PMT = contribution.","q5":"Is my data private?","a5":"Yes. All calculations are performed locally in your browser. Nothing is sent to any server."}