{"q1":"どのアニメーションプリセットが利用可能ですか？","a1":"8つのプリセット：バウンス（上下）、フェードイン（不透明度）、スライドイン（左から右）、回転（360°スピン）、パルス（スケール）、シェイク（水平）、ズームイン（0からスケール）、フリップ（3D Y軸回転）。","q2":"アニメーション速度をカスタマイズできますか？","a2":"はい、期間スライダーを使用してアニメーション速度を0.1秒から3秒に設定します。各プリセットは調整できる最適化されたデフォルト期間を持ちます。","q3":"タイミング関数とは何ですか？","a3":"タイミング関数はアニメーションの加速曲線を制御します。線形は一定速度で実行されます。イージングは遅く開始して加速し、その後遅くなります。イージングインは遅く開始します。イージングアウトは遅く終了します。イージングイン・イージングアウトはその両方を行います。","q4":"生成されたCSSをどのように使用しますか？","a4":"@keyframesルールとアニメーションプロパティを含む出力をコピーします。キーフレームをCSSファイルの上部に貼り付けて、アニメーションプロパティをエレメントセレクターに追加します。","q5":"アニメーション実行回数を設定できますか？","a5":"はい、インフィニティ（永遠にループ）、または1、2、3、5イテレーションから選択します。ローディングスピナーなどの連続エフェクトにはインフィニティを使用し、1回限りのエントランスアニメーションには固定数を使用します。"}